autonomize_observer/__init__.py
autonomize_observer/audit/__init__.py
autonomize_observer/audit/context.py
autonomize_observer/audit/logger.py
autonomize_observer/core/__init__.py
autonomize_observer/core/config.py
autonomize_observer/core/exceptions.py
autonomize_observer/core/imports.py
autonomize_observer/core/kafka_utils.py
autonomize_observer/cost/__init__.py
autonomize_observer/cost/pricing.py
autonomize_observer/exporters/__init__.py
autonomize_observer/exporters/base.py
autonomize_observer/exporters/kafka.py
autonomize_observer/exporters/kafka_base.py
autonomize_observer/integrations/__init__.py
autonomize_observer/integrations/fastapi.py
autonomize_observer/integrations/langflow.py
autonomize_observer/schemas/__init__.py
autonomize_observer/schemas/audit.py
autonomize_observer/schemas/base.py
autonomize_observer/schemas/enums.py
autonomize_observer/schemas/streaming.py
autonomize_observer/tracing/__init__.py
autonomize_observer/tracing/agent_tracer.py
autonomize_observer/tracing/base.py
autonomize_observer/tracing/factory.py
autonomize_observer/tracing/kafka_trace_producer.py
autonomize_observer/tracing/logfire_integration.py
autonomize_observer/tracing/otel_utils.py
autonomize_observer/tracing/workflow_tracer.py
autonomize_observer/tracing/utils/__init__.py
autonomize_observer/tracing/utils/model_utils.py
autonomize_observer/tracing/utils/serialization.py
autonomize_observer/tracing/utils/token_extractors.py
autonomize_observer-2.0.7.dist-info/METADATA
autonomize_observer-2.0.7.dist-info/WHEEL
autonomize_observer-2.0.7.dist-info/licenses/LICENSE
autonomize_observer-2.0.7.dist-info/RECORD
