Metadata-Version: 2.4
Name: autonomize-observer
Version: 2.0.7
Summary: Unified LLM Observability & Audit SDK - thin wrapper around Pydantic Logfire with Keycloak and Kafka support
Project-URL: Homepage, https://github.com/autonomize-ai/autonomize-observer
Project-URL: Repository, https://github.com/autonomize-ai/autonomize-observer.git
Author-email: Jagveer Singh <jagveer@autonomize.ai>
License: Proprietary
License-File: LICENSE
Keywords: audit,genai,kafka,keycloak,llm,logfire,observability,opentelemetry,tracing
Classifier: Development Status :: 4 - Beta
Classifier: Intended Audience :: Developers
Classifier: Programming Language :: Python :: 3.12
Classifier: Programming Language :: Python :: 3.13
Classifier: Topic :: Software Development :: Libraries :: Python Modules
Classifier: Topic :: System :: Monitoring
Requires-Python: >=3.12
Requires-Dist: confluent-kafka>=2.10.0
Requires-Dist: genai-prices>=0.0.40
Requires-Dist: logfire>=4.0.0
Requires-Dist: pydantic>=2.10.0
Requires-Dist: pyjwt>=2.10.0
Provides-Extra: all
Requires-Dist: anthropic>=0.40.0; extra == 'all'
Requires-Dist: fastapi>=0.115.0; extra == 'all'
Requires-Dist: openai>=1.50.0; extra == 'all'
Provides-Extra: anthropic
Requires-Dist: anthropic>=0.40.0; extra == 'anthropic'
Provides-Extra: fastapi
Requires-Dist: fastapi>=0.115.0; extra == 'fastapi'
Provides-Extra: openai
Requires-Dist: openai>=1.50.0; extra == 'openai'
